Workbook
Name NativeTimeline_Bill_date: #N/A
Name Slicer_Doctor_Full_Name: #N/A
Name Slicer_Hospital_branch: #N/A
Name Slicer_Payment_method: #N/A
Name Slicer_Payment_status: #N/A
Name Slicer_Reason_for_visit: #N/A
Name Slicer_Specialization: #N/A
Name Slicer_Status: #N/A
Name Slicer_Treatment_type: #N/A

Sheet Appointments
A1: appointment_id | B1: patient_id | C1: doctor_id | D1: appointment_date | E1: appointment_time | F1: reason_for_visit | G1: status
A2: A001 | B2: P034 | C2: D009 | D2: 45147 | E2: 0.63541667 | F2: Therapy | G2: Scheduled
A3: A002 | B3: P032 | C3: D004 | D3: 45086 | E3: 0.60416667 | F3: Therapy | G3: No-show
A4: A003 | B4: P048 | C4: D004 | D4: 45105 | E4: 0.33333333 | F4: Consultation | G4: Cancelled
A5: A004 | B5: P025 | C5: D006 | D5: 45170 | E5: 0.38541667 | F5: Consultation | G5: Cancelled
A6: A005 | B6: P040 | C6: D003 | D6: 45113 | E6: 0.53125 | F6: Emergency | G6: No-show
A7: A006 | B7: P045 | C7: D006 | D7: 45096 | E7: 0.67708333 | F7: Checkup | G7: Scheduled
A8: A007 | B8: P001 | C8: D007 | D8: 45025 | E8: 0.4375 | F8: Consultation | G8: Scheduled
A9: A008 | B9: P016 | C9: D010 | D9: 45070 | E9: 0.36458333 | F9: Consultation | G9: Cancelled
A10: A009 | B10: P039 | C10: D010 | D10: 44990 | E10: 0.57291667 | F10: Follow-up | G10: Scheduled
A11: A010 | B11: P005 | C11: D003 | D11: 44939 | E11: 0.64583333 | F11: Therapy | G11: Completed
A12: A011 | B12: P022 | C12: D007 | D12: 45242 | E12: 0.66666667 | F12: Checkup | G12: No-show
A13: A012 | B13: P029 | C13: D003 | D13: 45053 | E13: 0.41666667 | F13: Follow-up | G13: Completed
... A201: A200 | B201: P007 | C201: D005 | D201: 45290 | E201: 0.42708333 | F201: Consultation | G201: Cancelled

Sheet Patients
A1: patient_id | B1: first_name | C1: last_name | D1: gender | E1: date_of_birth | F1: contact_number | G1: address | H1: registration_date | I1: insurance_provider | J1: insurance_number | K1: email
A2: P001 | B2: David | C2: Williams | D2: F | E2: 20244 | F2: 6939585183 | G2: 789 Pine Rd | H2: 44735 | I2: WellnessCorp | J2: INS840674 | K2: david.williams@mail.com
A3: P002 | B3: Emily | C3: Smith | D3: F | E3: 30967 | F3: 8228188767 | G3: 321 Maple Dr | H3: 44576 | I3: PulseSecure | J3: INS354079 | K3: emily.smith@mail.com
A4: P003 | B4: Laura | C4: Jones | D4: M | E4: 28358 | F4: 8397029847 | G4: 321 Maple Dr | H4: 44599 | I4: PulseSecure | J4: INS650929 | K4: laura.jones@mail.com
A5: P004 | B5: Michael | C5: Johnson | D5: F | E5: 29637 | F5: 9019443432 | G5: 123 Elm St | H5: 44257 | I5: HealthIndia | J5: INS789944 | K5: michael.johnson@mail.com
A6: P005 | B6: David | C6: Wilson | D6: M | E6: 22090 | F6: 7734463155 | G6: 123 Elm St | H6: 44468 | I6: MedCare Plus | J6: INS788105 | K6: david.wilson@mail.com
A7: P006 | B7: Linda | C7: Jones | D7: M | E7: 23178 | F7: 7561777264 | G7: 321 Maple Dr | H7: 44836 | I7: HealthIndia | J7: INS613758 | K7: linda.jones@mail.com
A8: P007 | B8: Alex | C8: Johnson | D8: F | E8: 32667 | F8: 6278710077 | G8: 789 Pine Rd | H8: 44555 | I8: MedCare Plus | J8: INS465890 | K8: alex.johnson@mail.com
A9: P008 | B9: David | C9: Davis | D9: F | E9: 27946 | F9: 7090558393 | G9: 456 Oak Ave | H9: 44341 | I9: WellnessCorp | J9: INS545101 | K9: david.davis@mail.com
A10: P009 | B10: Laura | C10: Davis | D10: M | E10: 26278 | F10: 7060324619 | G10: 321 Maple Dr | H10: 44822 | I10: PulseSecure | J10: INS136631 | K10: laura.davis@mail.com
A11: P010 | B11: Michael | C11: Taylor | D11: M | E11: 37177 | F11: 7081396733 | G11: 123 Elm St | H11: 44797 | I11: WellnessCorp | J11: INS866577 | K11: michael.taylor@mail.com
A12: P011 | B12: Emily | C12: Jones | D12: F | E12: 24445 | F12: 8990604070 | G12: 789 Pine Rd | H12: 44831 | I12: MedCare Plus | J12: INS172991 | K12: emily.jones@mail.com
A13: P012 | B13: Laura | C13: Davis | D13: F | E13: 33580 | F13: 8135666049 | G13: 321 Maple Dr | H13: 45043 | I13: MedCare Plus | J13: INS104014 | K13: laura.davis@mail.com
... A51: P050 | B51: Laura | C51: Wilson | D51: M | E51: 34330 | F51: 8301134730 | G51: 321 Maple Dr | H51: 45044 | I51: WellnessCorp | J51: INS712210 | K51: laura.wilson@mail.com

Sheet Doctors
A1: doctor_id | B1: first_name | C1: last_name | D1: specialization | E1: phone_number | F1: years_experience | G1: hospital_branch | H1: email
A2: D001 | B2: David | C2: Taylor | D2: Dermatology | E2: 8322010158 | F2: 17 | G2: Westside Clinic | H2: dr.david.taylor@hospital.com
A3: D002 | B3: Jane | C3: Davis | D3: Pediatrics | E3: 9004382050 | F3: 24 | G3: Eastside Clinic | H3: dr.jane.davis@hospital.com
A4: D003 | B4: Jane | C4: Smith | D4: Pediatrics | E4: 8737740598 | F4: 19 | G4: Eastside Clinic | H4: dr.jane.smith@hospital.com
A5: D004 | B5: David | C5: Jones | D5: Pediatrics | E5: 6594221991 | F5: 28 | G5: Central Hospital | H5: dr.david.jones@hospital.com
A6: D005 | B6: Sarah | C6: Taylor | D6: Dermatology | E6: 9118538547 | F6: 26 | G6: Central Hospital | H6: dr.sarah.taylor@hospital.com
A7: D006 | B7: Alex | C7: Davis | D7: Pediatrics | E7: 6570137231 | F7: 23 | G7: Central Hospital | H7: dr.alex.davis@hospital.com
A8: D007 | B8: Robert | C8: Davis | D8: Oncology | E8: 8217493115 | F8: 26 | G8: Westside Clinic | H8: dr.robert.davis@hospital.com
A9: D008 | B9: Linda | C9: Brown | D9: Dermatology | E9: 9069162601 | F9: 5 | G9: Westside Clinic | H9: dr.linda.brown@hospital.com
A10: D009 | B10: Sarah | C10: Smith | D10: Pediatrics | E10: 7387087517 | F10: 26 | G10: Central Hospital | H10: dr.sarah.smith@hospital.com
A11: D010 | B11: Linda | C11: Wilson | D11: Oncology | E11: 6176383634 | F11: 21 | G11: Eastside Clinic | H11: dr.linda.wilson@hospital.com

Sheet Treatments
A1: appointment_id | B1: treatment_id | C1: treatment_type | D1: description | E1: cost | F1: treatment_date
A2: A001 | B2: T001 | C2: Chemotherapy | D2: Basic screening | E2: 3941.97 | F2: 45147
A3: A002 | B3: T002 | C3: MRI | D3: Advanced protocol | E3: 4158.44 | F3: 45086
A4: A003 | B4: T003 | C4: MRI | D4: Standard procedure | E4: 3731.55 | F4: 45105
A5: A004 | B5: T004 | C5: MRI | D5: Basic screening | E5: 4799.86 | F5: 45170
A6: A005 | B6: T005 | C6: ECG | D6: Standard procedure | E6: 582.05 | F6: 45113
A7: A006 | B7: T006 | C7: Chemotherapy | D7: Standard procedure | E7: 1381 | F7: 45096
A8: A007 | B8: T007 | C8: Chemotherapy | D8: Advanced protocol | E8: 534.03 | F8: 45025
A9: A008 | B9: T008 | C9: Physiotherapy | D9: Basic screening | E9: 3413.64 | F9: 45070
A10: A009 | B10: T009 | C10: Physiotherapy | D10: Standard procedure | E10: 4541.14 | F10: 44990
A11: A010 | B11: T010 | C11: Physiotherapy | D11: Standard procedure | E11: 1595.67 | F11: 44939
A12: A011 | B12: T011 | C12: MRI | D12: Basic screening | E12: 4671.66 | F12: 45242
A13: A012 | B13: T012 | C13: Chemotherapy | D13: Standard procedure | E13: 771.2 | F13: 45053
... A201: A200 | B201: T200 | C201: X-Ray | D201: Basic screening | E201: 3288.15 | F201: 45290

Sheet Billing
A1: patient_id | B1: bill_id | C1: treatment_id | D1: bill_date | E1: amount | F1: payment_method | G1: payment_status
A2: P034 | B2: B001 | C2: T001 | D2: 45147 | E2: 3941.97 | F2: Insurance | G2: Pending
A3: P032 | B3: B002 | C3: T002 | D3: 45086 | E3: 4158.44 | F3: Insurance | G3: Paid
A4: P048 | B4: B003 | C4: T003 | D4: 45105 | E4: 3731.55 | F4: Insurance | G4: Paid
A5: P025 | B5: B004 | C5: T004 | D5: 45170 | E5: 4799.86 | F5: Insurance | G5: Failed
A6: P040 | B6: B005 | C6: T005 | D6: 45113 | E6: 582.05 | F6: Credit Card | G6: Pending
A7: P045 | B7: B006 | C7: T006 | D7: 45096 | E7: 1381 | F7: Insurance | G7: Pending
A8: P001 | B8: B007 | C8: T007 | D8: 45025 | E8: 534.03 | F8: Cash | G8: Failed
A9: P016 | B9: B008 | C9: T008 | D9: 45070 | E9: 3413.64 | F9: Cash | G9: Failed
A10: P039 | B10: B009 | C10: T009 | D10: 44990 | E10: 4541.14 | F10: Credit Card | G10: Paid
A11: P005 | B11: B010 | C11: T010 | D11: 44939 | E11: 1595.67 | F11: Cash | G11: Paid
A12: P022 | B12: B011 | C12: T011 | D12: 45242 | E12: 4671.66 | F12: Cash | G12: Failed
A13: P029 | B13: B012 | C13: T012 | D13: 45053 | E13: 771.2 | F13: Insurance | G13: Pending
... A201: P007 | B201: B200 | C201: T200 | D201: 45290 | E201: 3288.15 | F201: Insurance | G201: Paid

Sheet Hospital Management Data
A1: Appointment_ID | B1: Patient_ID | C1: Patient Full Name | D1: Gender | E1: Date_of_birth | F1: Contact_number | G1: Address | H1: Registration_date | I1: Patient Email | J1: Doctor_ID | K1: Doctor Full Name | L1: Specialization | M1: Phone_number | N1: Hospital_branch | O1: Appointment_date | P1: Appointment_time | Q1: Reason_for_visit | R1: Status | S1: Treatment_ID | T1: Treatment_type | U1: Cost | V1: Treatment_date | W1: Bill_ID | X1: Bill_date | Y1: Amount | Z1: Payment_method | AA1: Payment_status
A2: A001 | B2: P034 | C2: Alex Smith | D2: =VLOOKUP(appointments7[[#This Row],[Patient_ID]],Patients!$A:$K,4,FALSE) -> F | E2: =VLOOKUP(appointments7[[#This Row],[Patient_ID]],Patients!$A:$K,5,FALSE) -> 18289 | F2: =VLOOKUP(appointments7[[#This Row],[Patient_ID]],Patients!$A:$K,6,FALSE) -> 8374657733 | G2: =VLOOKUP(appointments7[[#This Row],[Patient_ID]],Patients!$A:$K,7,FALSE) -> 321 Maple Dr | H2: =VLOOKUP(appointments7[[#This Row],[Patient_ID]],Patients!$A:$K,8,FALSE) -> 45095 | I2: =VLOOKUP(appointments7[[#This Row],[Patient_ID]],Patients!$A:$K,11,FALSE) -> alex.smith@mail.com | J2: D009 | K2: Sarah Smith | L2: =VLOOKUP(appointments7[[#This Row],[Doctor_ID]],Doctors!$A:$H,4,FALSE) -> Pediatrics | M2: =VLOOKUP(appointments7[[#This Row],[Doctor_ID]],Doctors!$A:$H,5,FALSE) -> 7387087517 | N2: =VLOOKUP(appointments7[[#This Row],[Doctor_ID]],Doctors!$A:$H,7,FALSE) -> Central Hospital | O2: 45147 | P2: 0.63541667 | Q2: Therapy | R2: Scheduled | S2: =VLOOKUP(appointments7[[#This Row],[Appointment_ID]],Treatments!$A:$F,2,FALSE) -> T001 | T2: =VLOOKUP(appointments7[[#This Row],[Appointment_ID]],Treatments!$A:$F,3,FALSE) -> Chemotherapy | U2: =VLOOKUP(treatments[[#This Row],[appointment_id]],Treatments!$A:$F,5,FALSE) -> 3941.97 | V2: =VLOOKUP(appointments7[[#This Row],[Appointment_ID]],Treatments!$A:$F,6,FALSE) -> 45147 | W2: =VLOOKUP(appointments7[[#This Row],[Patient_ID]],Billing!$A:$G,2,FALSE) -> B001 | X2: =VLOOKUP(appointments7[[#This Row],[Patient_ID]],Billing!$A:$H,4,FALSE) -> 45147 | Y2: =VLOOKUP(appointments7[[#This Row],[Patient_ID]],Billing!$A:$G,5,FALSE) -> 3941.97 | Z2: =VLOOKUP(appointments7[[#This Row],[Patient_ID]],Billing!$A:$G,6,FALSE) -> Insurance | AA2: =VLOOKUP(appointments7[[#This Row],[Patient_ID]],Billing!$A:$G,7,FALSE) -> Pending
A3: A002 | B3: P032 | C3: Alex Moore | D3: =VLOOKUP(appointments7[[#This Row],[Patient_ID]],Patients!$A:$K,4,FALSE) -> M | E3: =VLOOKUP(appointments7[[#This Row],[Patient_ID]],Patients!$A:$K,5,FALSE) -> 29594 | F3: =VLOOKUP(appointments7[[#This Row],[Patient_ID]],Patients!$A:$K,6,FALSE) -> 8102183595 | G3: =VLOOKUP(appointments7[[#This Row],[Patient_ID]],Patients!$A:$K,7,FALSE) -> 123 Elm St | H3: =VLOOKUP(appointments7[[#This Row],[Patient_ID]],Patients!$A:$K,8,FALSE) -> 44471 | I3: =VLOOKUP(appointments7[[#This Row],[Patient_ID]],Patients!$A:$K,11,FALSE) -> alex.moore@mail.com | J3: D004 | K3: David Jones | L3: =VLOOKUP(appointments7[[#This Row],[Doctor_ID]],Doctors!$A:$H,4,FALSE) -> Pediatrics | M3: =VLOOKUP(appointments7[[#This Row],[Doctor_ID]],Doctors!$A:$H,5,FALSE) -> 6594221991 | N3: =VLOOKUP(appointments7[[#This Row],[Doctor_ID]],Doctors!$A:$H,7,FALSE) -> Central Hospital | O3: 45086 | P3: 0.60416667 | Q3: Therapy | R3: No-show | S3: =VLOOKUP(appointments7[[#This Row],[Appointment_ID]],Treatments!$A:$F,2,FALSE) -> T002 | T3: =VLOOKUP(appointments7[[#This Row],[Appointment_ID]],Treatments!$A:$F,3,FALSE) -> MRI | U3: =VLOOKUP(treatments[[#This Row],[appointment_id]],Treatments!$A:$F,5,FALSE) -> 4158.44 | V3: =VLOOKUP(appointments7[[#This Row],[Appointment_ID]],Treatments!$A:$F,6,FALSE) -> 45086 | W3: =VLOOKUP(appointments7[[#This Row],[Patient_ID]],Billing!$A:$G,2,FALSE) -> B002 | X3: =VLOOKUP(appointments7[[#This Row],[Patient_ID]],Billing!$A:$H,4,FALSE) -> 45086 | Y3: =VLOOKUP(appointments7[[#This Row],[Patient_ID]],Billing!$A:$G,5,FALSE) -> 4158.44 | Z3: =VLOOKUP(appointments7[[#This Row],[Patient_ID]],Billing!$A:$G,6,FALSE) -> Insurance | AA3: =VLOOKUP(appointments7[[#This Row],[Patient_ID]],Billing!$A:$G,7,FALSE) -> Paid
A4: A003 | B4: P048 | C4: Emily Miller | D4: =VLOOKUP(appointments7[[#This Row],[Patient_ID]],Patients!$A:$K,4,FALSE) -> M | E4: =VLOOKUP(appointments7[[#This Row],[Patient_ID]],Patients!$A:$K,5,FALSE) -> 30399 | F4: =VLOOKUP(appointments7[[#This Row],[Patient_ID]],Patients!$A:$K,6,FALSE) -> 8720989381 | G4: =VLOOKUP(appointments7[[#This Row],[Patient_ID]],Patients!$A:$K,7,FALSE) -> 123 Elm St | H4: =VLOOKUP(appointments7[[#This Row],[Patient_ID]],Patients!$A:$K,8,FALSE) -> 45096 | I4: =VLOOKUP(appointments7[[#This Row],[Patient_ID]],Patients!$A:$K,11,FALSE) -> emily.miller@mail.com | J4: D004 | K4: David Jones | L4: =VLOOKUP(appointments7[[#This Row],[Doctor_ID]],Doctors!$A:$H,4,FALSE) -> Pediatrics | M4: =VLOOKUP(appointments7[[#This Row],[Doctor_ID]],Doctors!$A:$H,5,FALSE) -> 6594221991 | N4: =VLOOKUP(appointments7[[#This Row],[Doctor_ID]],Doctors!$A:$H,7,FALSE) -> Central Hospital | O4: 45105 | P4: 0.33333333 | Q4: Consultation | R4: Cancelled | S4: =VLOOKUP(appointments7[[#This Row],[Appointment_ID]],Treatments!$A:$F,2,FALSE) -> T003 | T4: =VLOOKUP(appointments7[[#This Row],[Appointment_ID]],Treatments!$A:$F,3,FALSE) -> MRI | U4: =VLOOKUP(treatments[[#This Row],[appointment_id]],Treatments!$A:$F,5,FALSE) -> 3731.55 | V4: =VLOOKUP(appointments7[[#This Row],[Appointment_ID]],Treatments!$A:$F,6,FALSE) -> 45105 | W4: =VLOOKUP(appointments7[[#This Row],[Patient_ID]],Billing!$A:$G,2,FALSE) -> B003 | X4: =VLOOKUP(appointments7[[#This Row],[Patient_ID]],Billing!$A:$H,4,FALSE) -> 45105 | Y4: =VLOOKUP(appointments7[[#This Row],[Patient_ID]],Billing!$A:$G,5,FALSE) -> 3731.55 | Z4: =VLOOKUP(appointments7[[#This Row],[Patient_ID]],Billing!$A:$G,6,FALSE) -> Insurance | AA4: =VLOOKUP(appointments7[[#This Row],[Patient_ID]],Billing!$A:$G,7,FALSE) -> Paid
A5: A004 | B5: P025 | C5: Robert Wilson | D5: =VLOOKUP(appointments7[[#This Row],[Patient_ID]],Patients!$A:$K,4,FALSE) -> M | E5: =VLOOKUP(appointments7[[#This Row],[Patient_ID]],Patients!$A:$K,5,FALSE) -> 24333 | F5: =VLOOKUP(appointments7[[#This Row],[Patient_ID]],Patients!$A:$K,6,FALSE) -> 7482069727 | G5: =VLOOKUP(appointments7[[#This Row],[Patient_ID]],Patients!$A:$K,7,FALSE) -> 123 Elm St | H5: =VLOOKUP(appointments7[[#This Row],[Patient_ID]],Patients!$A:$K,8,FALSE) -> 44448 | I5: =VLOOKUP(appointments7[[#This Row],[Patient_ID]],Patients!$A:$K,11,FALSE) -> robert.wilson@mail.com | J5: D006 | K5: Alex Davis | L5: =VLOOKUP(appointments7[[#This Row],[Doctor_ID]],Doctors!$A:$H,4,FALSE) -> Pediatrics | M5: =VLOOKUP(appointments7[[#This Row],[Doctor_ID]],Doctors!$A:$H,5,FALSE) -> 6570137231 | N5: =VLOOKUP(appointments7[[#This Row],[Doctor_ID]],Doctors!$A:$H,7,FALSE) -> Central Hospital | O5: 45170 | P5: 0.38541667 | Q5: Consultation | R5: Cancelled | S5: =VLOOKUP(appointments7[[#This Row],[Appointment_ID]],Treatments!$A:$F,2,FALSE) -> T004 | T5: =VLOOKUP(appointments7[[#This Row],[Appointment_ID]],Treatments!$A:$F,3,FALSE) -> MRI | U5: =VLOOKUP(treatments[[#This Row],[appointment_id]],Treatments!$A:$F,5,FALSE) -> 4799.86 | V5: =VLOOKUP(appointments7[[#This Row],[Appointment_ID]],Treatments!$A:$F,6,FALSE) -> 45170 | W5: =VLOOKUP(appointments7[[#This Row],[Patient_ID]],Billing!$A:$G,2,FALSE) -> B004 | X5: =VLOOKUP(appointments7[[#This Row],[Patient_ID]],Billing!$A:$H,4,FALSE) -> 45170 | Y5: =VLOOKUP(appointments7[[#This Row],[Patient_ID]],Billing!$A:$G,5,FALSE) -> 4799.86 | Z5: =VLOOKUP(appointments7[[#This Row],[Patient_ID]],Billing!$A:$G,6,FALSE) -> Insurance | AA5: =VLOOKUP(appointments7[[#This Row],[Patient_ID]],Billing!$A:$G,7,FALSE) -> Failed
A6: A005 | B6: P040 | C6: Emily Williams | D6: =VLOOKUP(appointments7[[#This Row],[Patient_ID]],Patients!$A:$K,4,FALSE) -> M | E6: =VLOOKUP(appointments7[[#This Row],[Patient_ID]],Patients!$A:$K,5,FALSE) -> 26449 | F6: =VLOOKUP(appointments7[[#This Row],[Patient_ID]],Patients!$A:$K,6,FALSE) -> 7587653815 | G6: =VLOOKUP(appointments7[[#This Row],[Patient_ID]],Patients!$A:$K,7,FALSE) -> 456 Oak Ave | H6: =VLOOKUP(appointments7[[#This Row],[Patient_ID]],Patients!$A:$K,8,FALSE) -> 44485 | I6: =VLOOKUP(appointments7[[#This Row],[Patient_ID]],Patients!$A:$K,11,FALSE) -> emily.williams@mail.com | J6: D003 | K6: Jane Smith | L6: =VLOOKUP(appointments7[[#This Row],[Doctor_ID]],Doctors!$A:$H,4,FALSE) -> Pediatrics | M6: =VLOOKUP(appointments7[[#This Row],[Doctor_ID]],Doctors!$A:$H,5,FALSE) -> 8737740598 | N6: =VLOOKUP(appointments7[[#This Row],[Doctor_ID]],Doctors!$A:$H,7,FALSE) -> Eastside Clinic | O6: 45113 | P6: 0.53125 | Q6: Emergency | R6: No-show | S6: =VLOOKUP(appointments7[[#This Row],[Appointment_ID]],Treatments!$A:$F,2,FALSE) -> T005 | T6: =VLOOKUP(appointments7[[#This Row],[Appointment_ID]],Treatments!$A:$F,3,FALSE) -> ECG | U6: =VLOOKUP(treatments[[#This Row],[appointment_id]],Treatments!$A:$F,5,FALSE) -> 582.05 | V6: =VLOOKUP(appointments7[[#This Row],[Appointment_ID]],Treatments!$A:$F,6,FALSE) -> 45113 | W6: =VLOOKUP(appointments7[[#This Row],[Patient_ID]],Billing!$A:$G,2,FALSE) -> B005 | X6: =VLOOKUP(appointments7[[#This Row],[Patient_ID]],Billing!$A:$H,4,FALSE) -> 45113 | Y6: =VLOOKUP(appointments7[[#This Row],[Patient_ID]],Billing!$A:$G,5,FALSE) -> 582.05 | Z6: =VLOOKUP(appointments7[[#This Row],[Patient_ID]],Billing!$A:$G,6,FALSE) -> Credit Card | AA6: =VLOOKUP(appointments7[[#This Row],[Patient_ID]],Billing!$A:$G,7,FALSE) -> Pending
A7: A006 | B7: P045 | C7: Linda Miller | D7: =VLOOKUP(appointments7[[#This Row],[Patient_ID]],Patients!$A:$K,4,FALSE) -> F | E7: =VLOOKUP(appointments7[[#This Row],[Patient_ID]],Patients!$A:$K,5,FALSE) -> 24222 | F7: =VLOOKUP(appointments7[[#This Row],[Patient_ID]],Patients!$A:$K,6,FALSE) -> 7579616535 | G7: =VLOOKUP(appointments7[[#This Row],[Patient_ID]],Patients!$A:$K,7,FALSE) -> 321 Maple Dr | H7: =VLOOKUP(appointments7[[#This Row],[Patient_ID]],Patients!$A:$K,8,FALSE) -> 44219 | I7: =VLOOKUP(appointments7[[#This Row],[Patient_ID]],Patients!$A:$K,11,FALSE) -> linda.miller@mail.com | J7: D006 | K7: Alex Davis | L7: =VLOOKUP(appointments7[[#This Row],[Doctor_ID]],Doctors!$A:$H,4,FALSE) -> Pediatrics | M7: =VLOOKUP(appointments7[[#This Row],[Doctor_ID]],Doctors!$A:$H,5,FALSE) -> 6570137231 | N7: =VLOOKUP(appointments7[[#This Row],[Doctor_ID]],Doctors!$A:$H,7,FALSE) -> Central Hospital | O7: 45096 | P7: 0.67708333 | Q7: Checkup | R7: Scheduled | S7: =VLOOKUP(appointments7[[#This Row],[Appointment_ID]],Treatments!$A:$F,2,FALSE) -> T006 | T7: =VLOOKUP(appointments7[[#This Row],[Appointment_ID]],Treatments!$A:$F,3,FALSE) -> Chemotherapy | U7: =VLOOKUP(treatments[[#This Row],[appointment_id]],Treatments!$A:$F,5,FALSE) -> 1381 | V7: =VLOOKUP(appointments7[[#This Row],[Appointment_ID]],Treatments!$A:$F,6,FALSE) -> 45096 | W7: =VLOOKUP(appointments7[[#This Row],[Patient_ID]],Billing!$A:$G,2,FALSE) -> B006 | X7: =VLOOKUP(appointments7[[#This Row],[Patient_ID]],Billing!$A:$H,4,FALSE) -> 45096 | Y7: =VLOOKUP(appointments7[[#This Row],[Patient_ID]],Billing!$A:$G,5,FALSE) -> 1381 | Z7: =VLOOKUP(appointments7[[#This Row],[Patient_ID]],Billing!$A:$G,6,FALSE) -> Insurance | AA7: =VLOOKUP(appointments7[[#This Row],[Patient_ID]],Billing!$A:$G,7,FALSE) -> Pending
A8: A007 | B8: P001 | C8: David Williams | D8: =VLOOKUP(appointments7[[#This Row],[Patient_ID]],Patients!$A:$K,4,FALSE) -> F | E8: =VLOOKUP(appointments7[[#This Row],[Patient_ID]],Patients!$A:$K,5,FALSE) -> 20244 | F8: =VLOOKUP(appointments7[[#This Row],[Patient_ID]],Patients!$A:$K,6,FALSE) -> 6939585183 | G8: =VLOOKUP(appointments7[[#This Row],[Patient_ID]],Patients!$A:$K,7,FALSE) -> 789 Pine Rd | H8: =VLOOKUP(appointments7[[#This Row],[Patient_ID]],Patients!$A:$K,8,FALSE) -> 44735 | I8: =VLOOKUP(appointments7[[#This Row],[Patient_ID]],Patients!$A:$K,11,FALSE) -> david.williams@mail.com | J8: D007 | K8: Robert Davis | L8: =VLOOKUP(appointments7[[#This Row],[Doctor_ID]],Doctors!$A:$H,4,FALSE) -> Oncology | M8: =VLOOKUP(appointments7[[#This Row],[Doctor_ID]],Doctors!$A:$H,5,FALSE) -> 8217493115 | N8: =VLOOKUP(appointments7[[#This Row],[Doctor_ID]],Doctors!$A:$H,7,FALSE) -> Westside Clinic | O8: 45025 | P8: 0.4375 | Q8: Consultation | R8: Scheduled | S8: =VLOOKUP(appointments7[[#This Row],[Appointment_ID]],Treatments!$A:$F,2,FALSE) -> T007 | T8: =VLOOKUP(appointments7[[#This Row],[Appointment_ID]],Treatments!$A:$F,3,FALSE) -> Chemotherapy | U8: =VLOOKUP(treatments[[#This Row],[appointment_id]],Treatments!$A:$F,5,FALSE) -> 534.03 | V8: =VLOOKUP(appointments7[[#This Row],[Appointment_ID]],Treatments!$A:$F,6,FALSE) -> 45025 | W8: =VLOOKUP(appointments7[[#This Row],[Patient_ID]],Billing!$A:$G,2,FALSE) -> B007 | X8: =VLOOKUP(appointments7[[#This Row],[Patient_ID]],Billing!$A:$H,4,FALSE) -> 45025 | Y8: =VLOOKUP(appointments7[[#This Row],[Patient_ID]],Billing!$A:$G,5,FALSE) -> 534.03 | Z8: =VLOOKUP(appointments7[[#This Row],[Patient_ID]],Billing!$A:$G,6,FALSE) -> Cash | AA8: =VLOOKUP(appointments7[[#This Row],[Patient_ID]],Billing!$A:$G,7,FALSE) -> Failed
A9: A008 | B9: P016 | C9: Michael Taylor | D9: =VLOOKUP(appointments7[[#This Row],[Patient_ID]],Patients!$A:$K,4,FALSE) -> M | E9: =VLOOKUP(appointments7[[#This Row],[Patient_ID]],Patients!$A:$K,5,FALSE) -> 36729 | F9: =VLOOKUP(appointments7[[#This Row],[Patient_ID]],Patients!$A:$K,6,FALSE) -> 7223380592 | G9: =VLOOKUP(appointments7[[#This Row],[Patient_ID]],Patients!$A:$K,7,FALSE) -> 789 Pine Rd | H9: =VLOOKUP(appointments7[[#This Row],[Patient_ID]],Patients!$A:$K,8,FALSE) -> 44400 | I9: =VLOOKUP(appointments7[[#This Row],[Patient_ID]],Patients!$A:$K,11,FALSE) -> michael.taylor@mail.com | J9: D010 | K9: Linda Wilson | L9: =VLOOKUP(appointments7[[#This Row],[Doctor_ID]],Doctors!$A:$H,4,FALSE) -> Oncology | M9: =VLOOKUP(appointments7[[#This Row],[Doctor_ID]],Doctors!$A:$H,5,FALSE) -> 6176383634 | N9: =VLOOKUP(appointments7[[#This Row],[Doctor_ID]],Doctors!$A:$H,7,FALSE) -> Eastside Clinic | O9: 45070 | P9: 0.36458333 | Q9: Consultation | R9: Cancelled | S9: =VLOOKUP(appointments7[[#This Row],[Appointment_ID]],Treatments!$A:$F,2,FALSE) -> T008 | T9: =VLOOKUP(appointments7[[#This Row],[Appointment_ID]],Treatments!$A:$F,3,FALSE) -> Physiotherapy | U9: =VLOOKUP(treatments[[#This Row],[appointment_id]],Treatments!$A:$F,5,FALSE) -> 3413.64 | V9: =VLOOKUP(appointments7[[#This Row],[Appointment_ID]],Treatments!$A:$F,6,FALSE) -> 45070 | W9: =VLOOKUP(appointments7[[#This Row],[Patient_ID]],Billing!$A:$G,2,FALSE) -> B008 | X9: =VLOOKUP(appointments7[[#This Row],[Patient_ID]],Billing!$A:$H,4,FALSE) -> 45070 | Y9: =VLOOKUP(appointments7[[#This Row],[Patient_ID]],Billing!$A:$G,5,FALSE) -> 3413.64 | Z9: =VLOOKUP(appointments7[[#This Row],[Patient_ID]],Billing!$A:$G,6,FALSE) -> Cash | AA9: =VLOOKUP(appointments7[[#This Row],[Patient_ID]],Billing!$A:$G,7,FALSE) -> Failed
A10: A009 | B10: P039 | C10: Jane Wilson | D10: =VLOOKUP(appointments7[[#This Row],[Patient_ID]],Patients!$A:$K,4,FALSE) -> F | E10: =VLOOKUP(appointments7[[#This Row],[Patient_ID]],Patients!$A:$K,5,FALSE) -> 18609 | F10: =VLOOKUP(appointments7[[#This Row],[Patient_ID]],Patients!$A:$K,6,FALSE) -> 9271131338 | G10: =VLOOKUP(appointments7[[#This Row],[Patient_ID]],Patients!$A:$K,7,FALSE) -> 789 Pine Rd | H10: =VLOOKUP(appointments7[[#This Row],[Patient_ID]],Patients!$A:$K,8,FALSE) -> 44264 | I10: =VLOOKUP(appointments7[[#This Row],[Patient_ID]],Patients!$A:$K,11,FALSE) -> jane.wilson@mail.com | J10: D010 | K10: Linda Wilson | L10: =VLOOKUP(appointments7[[#This Row],[Doctor_ID]],Doctors!$A:$H,4,FALSE) -> Oncology | M10: =VLOOKUP(appointments7[[#This Row],[Doctor_ID]],Doctors!$A:$H,5,FALSE) -> 6176383634 | N10: =VLOOKUP(appointments7[[#This Row],[Doctor_ID]],Doctors!$A:$H,7,FALSE) -> Eastside Clinic | O10: 44990 | P10: 0.57291667 | Q10: Follow-up | R10: Scheduled | S10: =VLOOKUP(appointments7[[#This Row],[Appointment_ID]],Treatments!$A:$F,2,FALSE) -> T009 | T10: =VLOOKUP(appointments7[[#This Row],[Appointment_ID]],Treatments!$A:$F,3,FALSE) -> Physiotherapy | U10: =VLOOKUP(treatments[[#This Row],[appointment_id]],Treatments!$A:$F,5,FALSE) -> 4541.14 | V10: =VLOOKUP(appointments7[[#This Row],[Appointment_ID]],Treatments!$A:$F,6,FALSE) -> 44990 | W10: =VLOOKUP(appointments7[[#This Row],[Patient_ID]],Billing!$A:$G,2,FALSE) -> B009 | X10: =VLOOKUP(appointments7[[#This Row],[Patient_ID]],Billing!$A:$H,4,FALSE) -> 44990 | Y10: =VLOOKUP(appointments7[[#This Row],[Patient_ID]],Billing!$A:$G,5,FALSE) -> 4541.14 | Z10: =VLOOKUP(appointments7[[#This Row],[Patient_ID]],Billing!$A:$G,6,FALSE) -> Credit Card | AA10: =VLOOKUP(appointments7[[#This Row],[Patient_ID]],Billing!$A:$G,7,FALSE) -> Paid
A11: A010 | B11: P005 | C11: David Wilson | D11: =VLOOKUP(appointments7[[#This Row],[Patient_ID]],Patients!$A:$K,4,FALSE) -> M | E11: =VLOOKUP(appointments7[[#This Row],[Patient_ID]],Patients!$A:$K,5,FALSE) -> 22090 | F11: =VLOOKUP(appointments7[[#This Row],[Patient_ID]],Patients!$A:$K,6,FALSE) -> 7734463155 | G11: =VLOOKUP(appointments7[[#This Row],[Patient_ID]],Patients!$A:$K,7,FALSE) -> 123 Elm St | H11: =VLOOKUP(appointments7[[#This Row],[Patient_ID]],Patients!$A:$K,8,FALSE) -> 44468 | I11: =VLOOKUP(appointments7[[#This Row],[Patient_ID]],Patients!$A:$K,11,FALSE) -> david.wilson@mail.com | J11: D003 | K11: Jane Smith | L11: =VLOOKUP(appointments7[[#This Row],[Doctor_ID]],Doctors!$A:$H,4,FALSE) -> Pediatrics | M11: =VLOOKUP(appointments7[[#This Row],[Doctor_ID]],Doctors!$A:$H,5,FALSE) -> 8737740598 | N11: =VLOOKUP(appointments7[[#This Row],[Doctor_ID]],Doctors!$A:$H,7,FALSE) -> Eastside Clinic | O11: 44939 | P11: 0.64583333 | Q11: Therapy | R11: Completed | S11: =VLOOKUP(appointments7[[#This Row],[Appointment_ID]],Treatments!$A:$F,2,FALSE) -> T010 | T11: =VLOOKUP(appointments7[[#This Row],[Appointment_ID]],Treatments!$A:$F,3,FALSE) -> Physiotherapy | U11: =VLOOKUP(treatments[[#This Row],[appointment_id]],Treatments!$A:$F,5,FALSE) -> 1595.67 | V11: =VLOOKUP(appointments7[[#This Row],[Appointment_ID]],Treatments!$A:$F,6,FALSE) -> 44939 | W11: =VLOOKUP(appointments7[[#This Row],[Patient_ID]],Billing!$A:$G,2,FALSE) -> B010 | X11: =VLOOKUP(appointments7[[#This Row],[Patient_ID]],Billing!$A:$H,4,FALSE) -> 44939 | Y11: =VLOOKUP(appointments7[[#This Row],[Patient_ID]],Billing!$A:$G,5,FALSE) -> 1595.67 | Z11: =VLOOKUP(appointments7[[#This Row],[Patient_ID]],Billing!$A:$G,6,FALSE) -> Cash | AA11: =VLOOKUP(appointments7[[#This Row],[Patient_ID]],Billing!$A:$G,7,FALSE) -> Paid
A12: A011 | B12: P022 | C12: John Brown | D12: =VLOOKUP(appointments7[[#This Row],[Patient_ID]],Patients!$A:$K,4,FALSE) -> M | E12: =VLOOKUP(appointments7[[#This Row],[Patient_ID]],Patients!$A:$K,5,FALSE) -> 20219 | F12: =VLOOKUP(appointments7[[#This Row],[Patient_ID]],Patients!$A:$K,6,FALSE) -> 6221099573 | G12: =VLOOKUP(appointments7[[#This Row],[Patient_ID]],Patients!$A:$K,7,FALSE) -> 321 Maple Dr | H12: =VLOOKUP(appointments7[[#This Row],[Patient_ID]],Patients!$A:$K,8,FALSE) -> 44327 | I12: =VLOOKUP(appointments7[[#This Row],[Patient_ID]],Patients!$A:$K,11,FALSE) -> john.brown@mail.com | J12: D007 | K12: Robert Davis | L12: =VLOOKUP(appointments7[[#This Row],[Doctor_ID]],Doctors!$A:$H,4,FALSE) -> Oncology | M12: =VLOOKUP(appointments7[[#This Row],[Doctor_ID]],Doctors!$A:$H,5,FALSE) -> 8217493115 | N12: =VLOOKUP(appointments7[[#This Row],[Doctor_ID]],Doctors!$A:$H,7,FALSE) -> Westside Clinic | O12: 45242 | P12: 0.66666667 | Q12: Checkup | R12: No-show | S12: =VLOOKUP(appointments7[[#This Row],[Appointment_ID]],Treatments!$A:$F,2,FALSE) -> T011 | T12: =VLOOKUP(appointments7[[#This Row],[Appointment_ID]],Treatments!$A:$F,3,FALSE) -> MRI | U12: =VLOOKUP(treatments[[#This Row],[appointment_id]],Treatments!$A:$F,5,FALSE) -> 4671.66 | V12: =VLOOKUP(appointments7[[#This Row],[Appointment_ID]],Treatments!$A:$F,6,FALSE) -> 45242 | W12: =VLOOKUP(appointments7[[#This Row],[Patient_ID]],Billing!$A:$G,2,FALSE) -> B011 | X12: =VLOOKUP(appointments7[[#This Row],[Patient_ID]],Billing!$A:$H,4,FALSE) -> 45242 | Y12: =VLOOKUP(appointments7[[#This Row],[Patient_ID]],Billing!$A:$G,5,FALSE) -> 4671.66 | Z12: =VLOOKUP(appointments7[[#This Row],[Patient_ID]],Billing!$A:$G,6,FALSE) -> Cash | AA12: =VLOOKUP(appointments7[[#This Row],[Patient_ID]],Billing!$A:$G,7,FALSE) -> Failed
A13: A012 | B13: P029 | C13: David Smith | D13: =VLOOKUP(appointments7[[#This Row],[Patient_ID]],Patients!$A:$K,4,FALSE) -> M | E13: =VLOOKUP(appointments7[[#This Row],[Patient_ID]],Patients!$A:$K,5,FALSE) -> 38487 | F13: =VLOOKUP(appointments7[[#This Row],[Patient_ID]],Patients!$A:$K,6,FALSE) -> 8923607677 | G13: =VLOOKUP(appointments7[[#This Row],[Patient_ID]],Patients!$A:$K,7,FALSE) -> 789 Pine Rd | H13: =VLOOKUP(appointments7[[#This Row],[Patient_ID]],Patients!$A:$K,8,FALSE) -> 45035 | I13: =VLOOKUP(appointments7[[#This Row],[Patient_ID]],Patients!$A:$K,11,FALSE) -> david.smith@mail.com | J13: D003 | K13: Jane Smith | L13: =VLOOKUP(appointments7[[#This Row],[Doctor_ID]],Doctors!$A:$H,4,FALSE) -> Pediatrics | M13: =VLOOKUP(appointments7[[#This Row],[Doctor_ID]],Doctors!$A:$H,5,FALSE) -> 8737740598 | N13: =VLOOKUP(appointments7[[#This Row],[Doctor_ID]],Doctors!$A:$H,7,FALSE) -> Eastside Clinic | O13: 45053 | P13: 0.41666667 | Q13: Follow-up | R13: Completed | S13: =VLOOKUP(appointments7[[#This Row],[Appointment_ID]],Treatments!$A:$F,2,FALSE) -> T012 | T13: =VLOOKUP(appointments7[[#This Row],[Appointment_ID]],Treatments!$A:$F,3,FALSE) -> Chemotherapy | U13: =VLOOKUP(treatments[[#This Row],[appointment_id]],Treatments!$A:$F,5,FALSE) -> 771.2 | V13: =VLOOKUP(appointments7[[#This Row],[Appointment_ID]],Treatments!$A:$F,6,FALSE) -> 45053 | W13: =VLOOKUP(appointments7[[#This Row],[Patient_ID]],Billing!$A:$G,2,FALSE) -> B012 | X13: =VLOOKUP(appointments7[[#This Row],[Patient_ID]],Billing!$A:$H,4,FALSE) -> 45053 | Y13: =VLOOKUP(appointments7[[#This Row],[Patient_ID]],Billing!$A:$G,5,FALSE) -> 771.2 | Z13: =VLOOKUP(appointments7[[#This Row],[Patient_ID]],Billing!$A:$G,6,FALSE) -> Insurance | AA13: =VLOOKUP(appointments7[[#This Row],[Patient_ID]],Billing!$A:$G,7,FALSE) -> Pending
... A201: A200 | B201: P007 | C201: Alex Johnson | D201: =VLOOKUP(appointments7[[#This Row],[Patient_ID]],Patients!$A:$K,4,FALSE) -> F | E201: =VLOOKUP(appointments7[[#This Row],[Patient_ID]],Patients!$A:$K,5,FALSE) -> 32667 | F201: =VLOOKUP(appointments7[[#This Row],[Patient_ID]],Patients!$A:$K,6,FALSE) -> 6278710077 | G201: =VLOOKUP(appointments7[[#This Row],[Patient_ID]],Patients!$A:$K,7,FALSE) -> 789 Pine Rd | H201: =VLOOKUP(appointments7[[#This Row],[Patient_ID]],Patients!$A:$K,8,FALSE) -> 44555 | I201: =VLOOKUP(appointments7[[#This Row],[Patient_ID]],Patients!$A:$K,11,FALSE) -> alex.johnson@mail.com | J201: D005 | K201: Sarah Taylor | L201: =VLOOKUP(appointments7[[#This Row],[Doctor_ID]],Doctors!$A:$H,4,FALSE) -> Dermatology | M201: =VLOOKUP(appointments7[[#This Row],[Doctor_ID]],Doctors!$A:$H,5,FALSE) -> 9118538547 | N201: =VLOOKUP(appointments7[[#This Row],[Doctor_ID]],Doctors!$A:$H,7,FALSE) -> Central Hospital | O201: 45290 | P201: 0.42708333 | Q201: Consultation | R201: Cancelled | S201: =VLOOKUP(appointments7[[#This Row],[Appointment_ID]],Treatments!$A:$F,2,FALSE) -> T200 | T201: =VLOOKUP(appointments7[[#This Row],[Appointment_ID]],Treatments!$A:$F,3,FALSE) -> X-Ray | U201: =VLOOKUP(treatments[[#This Row],[appointment_id]],Treatments!$A:$F,5,FALSE) -> 3288.15 | V201: =VLOOKUP(appointments7[[#This Row],[Appointment_ID]],Treatments!$A:$F,6,FALSE) -> 45290 | W201: =VLOOKUP(appointments7[[#This Row],[Patient_ID]],Billing!$A:$G,2,FALSE) -> B095 | X201: =VLOOKUP(appointments7[[#This Row],[Patient_ID]],Billing!$A:$H,4,FALSE) -> 45055 | Y201: =VLOOKUP(appointments7[[#This Row],[Patient_ID]],Billing!$A:$G,5,FALSE) -> 2097.48 | Z201: =VLOOKUP(appointments7[[#This Row],[Patient_ID]],Billing!$A:$G,6,FALSE) -> Cash | AA201: =VLOOKUP(appointments7[[#This Row],[Patient_ID]],Billing!$A:$G,7,FALSE) -> Failed

Sheet Changelog
B9: STEP | C9: SHEET | D9: CHANGE MADE | E9: REASON
B10: 1 | C10: All datasets | D10: Checked Duplicate appointment IDs, bill IDs & treatment IDs - No duplicates found | E10: To ensure each record is unique & avoid duplicate records in analysis
B11: 2 | C11: All datasets | D11: Checked Missing Values - No missing values found | E11: To ensure the dataset is complete & suitable for analysis
B12: 3 | C12: Hospital management data | D12: Combined patient information with appointment data using VLOOKUP | E12: To connect patient details with appointment records
B13: 4 | C13: Hospital management data | D13: Added doctor information using VLOOKUP | E13: To connect doctor details with appointment records for doctor & specialization analysis
B14: 5 | C14: Hospital management data | D14: Added treatment information using VLOOKUP | E14: To connect treatment details & cost with appointment records
B15: 6 | C15: Hospital management data | D15: Added Billing information using VLOOKUP | E15: To connect billing details with the relevant appointment records
B16: 7 | C16: Hospital management data | D16: Combined patient first name and last name using CONCAT Function | E16: To create a complete patient name for easier identification & analysis
B17: 8 | C17: Hospital management data | D17: Combined Doctor first name and last name using CONCAT Function | E17: To create a complete docctor name for easier identification & analysis
B18: 9 | C18: Hospital management data | D18: Checked & Standardized data types : Dates as DATE, Appointment time as TIME, Phone/Contact numbers as TEXT and Treatment cost / Bill Amount as CURRENCY | E18: To ensure consistent data types and accurate calculations

Sheet Analysis 
B8: 1 | C8: How many appointments were recorded
B9: 2 | C9: What percentage of appointments were no-shows
B10: 3 | C10: What is the appointment completion rate
B11: 4 | C11: What is the total billing amount
B12: 5 | C12: How much of the billing amount has been paid
B13: 6 | C13: What percentage of the total billing amount has been paid
B14: 7 | C14: What is the average treatment cost
B15: 8 | C15: Which treatment generates the highest total treatment cost
B17: 9 | C17: What is the distribution of appointments by status?
B18: 10 | C18: How does appointment status differ by specialization?
B19: 11 | C19: Which doctor handles the highest number of appointments
B20: 12 | C20: How do appointment statuses vary across hospital branches?
... B22: 14 | C22: How does total billing change over time?

Sheet Calculation
C10: Sl No | D10: QUESTIONS | E10: CALCULATIONS
C11: 1 | D11: How many appointments were recorded | E11: =COUNTA(appointments7[Appointment_ID]) -> 200
C12: 2 | D12: What percentage of appointments were no-shows | E12: =COUNTIF(appointments7[Status],'Hospital Management Data'!R187)/Calculation!E11 -> 0.26
C13: 3 | D13: What is the appointment completion rate | E13: =COUNTIF(appointments7[Status],'Hospital Management Data'!R174)/Calculation!E11 -> 0.23
C14: 4 | D14: What is the total billing amount | E14: =SUM(appointments7[Amount]) -> 522420.07
C15: 5 | D15: How much of the billing amount has been paid | E15: =SUMIF(appointments7[Payment_status],'Hospital Management Data'!AA183,appointments7[Amount]) -> 188674.04
C16: 6 | D16: What percentage of the total billing amount has been paid | E16: =E15/E14 -> 0.36115389
C17: 7 | D17: What is the average treatment cost | E17: =AVERAGE(appointments7[Cost]) -> 2756.2493
C18: 8 | D18: Which treatment generates the highest total treatment cost | E18: Chemotherapy | F18: Chemotherapy | G18: =SUMIF('Hospital Management Data'!$T$2:$T$202,Calculation!F18,'Hospital Management Data'!$U$2:$U$202) -> 128855.68
F19: ECG | G19: =SUMIF('Hospital Management Data'!$T$2:$T$202,Calculation!F19,'Hospital Management Data'!$U$2:$U$202) -> 96224.24
F20: MRI | G20: =SUMIF('Hospital Management Data'!$T$2:$T$202,Calculation!F20,'Hospital Management Data'!$U$2:$U$202) -> 116098.16
F21: Physiotherapy | G21: =SUMIF('Hospital Management Data'!$T$2:$T$202,Calculation!F21,'Hospital Management Data'!$U$2:$U$202) -> 99418.1
F22: X-Ray | G22: =SUMIF('Hospital Management Data'!$T$2:$T$202,Calculation!F22,'Hospital Management Data'!$U$2:$U$202) -> 110653.67

Sheet PIVOT
B7: TOTAL APPOINTMENTS | C7: =GETPIVOTDATA("Appointment_id",$B$14) -> 6 | E7: Appointment status by specialization | H7: Doctor
B8: TOTAL BILL AMOUNT | C8: =GETPIVOTDATA("Amount",$B$23) -> 15628.27 | E8: Row Labels | F8: Count of Appointment_id | H8: Row Labels | I8: Count of Appointment_id
B9: COMPLETION RATE | C9: =GETPIVOTDATA("Appointment_id",$B$33,"Status","Completed") -> 0.16666667 | E9: Dermatology | F9: 6 | H9: Sarah Taylor | I9: 6
B10: NO SHOW RATE | C10: =GETPIVOTDATA("Appointment_id",$B$33,"Status","No-show") -> #REF! | E10: Grand Total | F10: 6 | H10: Grand Total | I10: 6
B11: AVERAGE TREATMENT COST | C11: =GETPIVOTDATA("Cost",$H$23) -> 2662.6867
B13: Appointment Status
B14: Row Labels | C14: Count of Appointment_id
B15: Cancelled | C15: 1 | E15: Appointment status by Branch
B16: Completed | C16: 1 | E16: Row Labels | F16: Count of Appointment_id
B17: Scheduled | C17: 4 | E17: Central Hospital | F17: 6
B18: Grand Total | C18: 6 | E18: Grand Total | F18: 6
B22: Treatment - Billing amount | H22: Treatment - Billing amount
B23: Row Labels | C23: Sum of Amount | E23: Month - Billing amount | H23: Row Labels | I23: Average of Cost
B24: Chemotherapy | C24: 15628.27 | E24: Row Labels | F24: Sum of Amount | H24: Chemotherapy | I24: 2662.6867
B25: Grand Total | C25: 15628.27 | E25: Jan | F25: 956.39 | H25: Grand Total | I25: 2662.6867
E26: Feb | F26: 1565.92
E27: May | F27: 3815.93
E28: Jun | F28: 5103.68
E29: Sep | F29: 4186.35
E30: Grand Total | F30: 15628.27
B32: Appointment Status
B33: Row Labels | C33: Count of Appointment_id
B34: Cancelled | C34: 0.16666667
B35: Completed | C35: 0.16666667
B36: Scheduled | C36: 0.66666667
B37: Grand Total | C37: 1

Sheet Charts

Sheet Dashboard

Sheet Insights & Recommendations
E8: INSIGHTS | F8: RECOMMENDATIONS
E9: Only 23% of appointments are completed, while 26% are no-shows. | F9: The hospital can send appointment reminders & confirmation messages to reduce no-shows.
E10: Central Hospital has the highest number of appointments (84). | F10: Adequate doctors , staff & facilities should be allocated to Central Hospital according to the higher patient demand.
E11: Pediatrics has the highest number of appointments (98). | F11: More consultation slots and resources can be provided to the Pediatrics department.
E12: DR Sarah Taylor handles the highest number of appointments (29). | F12: Doctor workload should be monitored and appointments can be distributed more evenly when necessary.
E13: There are 45 Checkup appointments, the highest among the reasons for visit. | F13: The hospital can ensure enough consultation capacity for routine checkups.
E14: X-RAY has the highest number of no-shows among treatment types. | F14: The hospital could confirm X-RAY appointments in advance and allow easy rescheduling.
E15: Cental Hospital has 31% no-shows, the highest among the 3 branches. | F15: Management should investigate the reasons for the hight no-show rate at Central Hospital strengthen appointment reminders.
E16: Pediatrics has 98 appointments, but also 25% cancellations and 26% no-shows. | F16: The hospital should review appointment scheduling in Pediatrics and improve confirmation and rescheduling procedures.
E17: Chemotherapy generates the highest total billing amount (₹ 1,15,183.68) | F17: The hospital can monitor demand and resource requirements for high-revenue treatments such as chemotherapy.
E18: Only about 36% of the total billing amount has been paid. | F18: The hospital should follow up on pending payments and failed transactions to improve payment collection and cash flow.
E19: MRI has a high average treatment cost compared with the other treatments. | F19: The hospital should monitor MRI utilization and pricing to maintain efficient service delivery.
... E27: After reaching its peak in May, billing declines sharply in June & July before recovering in August and September | F27: Management should compare these months using the Month, Treatement Type, Branch and Status to identify the specific factors behind the decline & recovery.
